ai_character/__init__.py
ai_character/ai_character.py
ai_character/ai_character_agent.py
ai_character/audio_processor.py
ai_character/model_handlers.py
ai_character-0.1.8.dist-info/LICENSE
ai_character-0.1.8.dist-info/METADATA
ai_character-0.1.8.dist-info/WHEEL
ai_character-0.1.8.dist-info/top_level.txt
ai_character-0.1.8.dist-info/RECORD
