Metadata-Version: 2.1
Name: ai-character
Version: 0.1.8
Summary: A Python package for creating interactive AI characters
Author-email: Sid Uppal <siddhu@gmail.com>
License: MIT License
Project-URL: Homepage, https://github.com/sidu/ai_character
Classifier: Programming Language :: Python :: 3
Classifier: License :: OSI Approved :: MIT License
Classifier: Operating System :: OS Independent
Requires-Python: >=3.8
License-File: LICENSE
Requires-Dist: openai
Requires-Dist: sounddevice
Requires-Dist: numpy
Requires-Dist: pygame
Requires-Dist: pydub
Requires-Dist: elevenlabs
Requires-Dist: pyyaml
Requires-Dist: opencv-python
Requires-Dist: groq
Requires-Dist: ollama
Requires-Dist: scipy
